{
    "info": {
		"_postman_id"   : "d9bc3afc-fd40-5505-b57f-8f5d5118e01b",
		"name"          : "@app - common/administrative-area-level-3",
		"schema"        : "https://schema.getpostman.com/json/collection/v2.1.0/collection.json"
    },
    "item": [
        {
			"name": "GraphQL - commonCreateAdministrativeAreaLevel3",
			"request": {
				"method": "POST",
				"header": [
                ],
				"body": {
					"mode": "graphql",
					"graphql": {
						"query": "mutation ($payload:CommonCreateAdministrativeAreaLevel3Input!)\n{\n\tcommonCreateAdministrativeAreaLevel3 (payload:$payload)\n\t{\n\t\tid\n\t\tcountryId\n\t\tadministrativeAreaLevel1Id\n\t\tadministrativeAreaLevel2Id\n\t\tcode\n\t\tcustomCode\n\t\tname\n\t\tslug\n\t\tlatitude\n\t\tlongitude\n\t\tzoom\n\t\tmapType\n\t}\n}",
                        "variables": "{\n\t\"payload\":\n\t{\n\t\t\"id\": \"5b19d6ac-4081-573b-96b3-56964d5326a8\", \n\t\t\"countryId\": \"5b19d6ac-4081-573b-96b3-56964d5326a8\", \n\t\t\"administrativeAreaLevel1Id\": \"5b19d6ac-4081-573b-96b3-56964d5326a8\", \n\t\t\"administrativeAreaLevel2Id\": \"5b19d6ac-4081-573b-96b3-56964d5326a8\", \n\t\t\"code\": \"caqyck5\", \n\t\t\"customCode\": \"00sl1vaoa\", \n\t\t\"name\": \"Licensed Metal Car\", \n\t\t\"slug\": \"quas-deserunt-velit\", \n\t\t\"latitude\": 52.26029566524504, \n\t\t\"longitude\": 177.77588351638553, \n\t\t\"zoom\": 6, \n\t\t\"mapType\": 'TERRAIN'\n\t}\n}"
					}
				},
				"url": {
					"raw": "{{URL}}/graphql",
					"host": [
						"{{URL}}"
					],
					"path": [
						"graphql"
					]
				}
			},
			"response": []
        },
        {
			"name": "GraphQL - commonCreateAdministrativeAreasLevel3",
			"request": {
				"method": "POST",
				"header": [],
				"body": {
					"mode": "graphql",
					"graphql": {
						"query": "mutation ($payload:[CommonCreateAdministrativeAreaLevel3Input]!)\n{\n\tcommonCreateAdministrativeAreasLevel3 (payload:$payload)\n}",
						"variables": "{\n\t\"payload\":\n\t[\n\t\t{\n\t\t\t\"id\": \"b61ac801-3a0c-4e4b-863b-d9cb1b37da5f\", \n\t\t\t\"countryId\": \"46c00f1d-33c7-45c3-be83-19014285a96e\", \n\t\t\t\"administrativeAreaLevel1Id\": \"067dbca8-6f74-4f1c-8d2f-d175b7653006\", \n\t\t\t\"administrativeAreaLevel2Id\": \"dcfe97fd-b950-4e53-a421-c4962ea95c50\", \n\t\t\t\"code\": \"h3ogwke\", \n\t\t\t\"customCode\": \"gkvwozyoa\", \n\t\t\t\"name\": \"Small Granite Pants\", \n\t\t\t\"slug\": \"omnis-porro-earum\", \n\t\t\t\"latitude\": 94.30346374428427, \n\t\t\t\"longitude\": 107.40470242317642, \n\t\t\t\"zoom\": 6, \n\t\t\t\"mapType\": 'TERRAIN'\n\t\t}, \n\t\t{\n\t\t\t\"id\": \"65ac2d45-1017-4ae1-8bf3-e4ae25cdf81d\", \n\t\t\t\"countryId\": \"ee492772-19f0-47ca-be39-20fab59bb80c\", \n\t\t\t\"administrativeAreaLevel1Id\": \"06868f9f-9da0-4e6d-a683-d4738568259e\", \n\t\t\t\"administrativeAreaLevel2Id\": \"d4a86f06-2d68-44f0-b35c-6fdecc269f32\", \n\t\t\t\"code\": \"qwqolsy\", \n\t\t\t\"customCode\": \"az0hk1vrz\", \n\t\t\t\"name\": \"Handmade Cotton Keyboard\", \n\t\t\t\"slug\": \"sint-adipisci-quis\", \n\t\t\t\"latitude\": 79.1800119935555, \n\t\t\t\"longitude\": 992.24916748764, \n\t\t\t\"zoom\": 4, \n\t\t\t\"mapType\": 'SATELLITE'\n\t\t}, \n\t\t{\n\t\t\t\"id\": \"30e66dfc-d7ec-4ce4-85aa-cd8b2c0ceb7a\", \n\t\t\t\"countryId\": \"7372e3ab-96dd-4b35-a9f7-76277f4557b4\", \n\t\t\t\"administrativeAreaLevel1Id\": \"4735f869-afa7-4e73-b1a9-eeaf3244e576\", \n\t\t\t\"administrativeAreaLevel2Id\": \"54564f4c-d7e6-46c4-98a5-2d4ca89b65da\", \n\t\t\t\"code\": \"dlt2p7q\", \n\t\t\t\"customCode\": \"8cez0nrk1\", \n\t\t\t\"name\": \"Sleek Wooden Keyboard\", \n\t\t\t\"slug\": \"qui-magni-voluptatem\", \n\t\t\t\"latitude\": 85.32313928972958, \n\t\t\t\"longitude\": 708.7858552558986, \n\t\t\t\"zoom\": 9, \n\t\t\t\"mapType\": 'ROADMAP'\n\t\t}, \n\t\t{\n\t\t\t\"id\": \"ad079749-e5e4-46b7-98cf-45c9118aeaf7\", \n\t\t\t\"countryId\": \"b64b8e62-4e2b-4022-a272-96265c0a8468\", \n\t\t\t\"administrativeAreaLevel1Id\": \"60dfbc7e-4f7b-49b7-8b28-47aaf1a534d4\", \n\t\t\t\"administrativeAreaLevel2Id\": \"a6e5fb44-c16a-4360-b244-81e87ca47a07\", \n\t\t\t\"code\": \"bjwmvl8\", \n\t\t\t\"customCode\": \"talv9mcui\", \n\t\t\t\"name\": \"Awesome Steel Pants\", \n\t\t\t\"slug\": \"et-nihil-ea\", \n\t\t\t\"latitude\": 22.66294276400198, \n\t\t\t\"longitude\": 322.615865726149, \n\t\t\t\"zoom\": 2, \n\t\t\t\"mapType\": 'SATELLITE'\n\t\t}, \n\t\t{\n\t\t\t\"id\": \"9ef5a29a-df0a-4beb-bc4f-0e463a4d1151\", \n\t\t\t\"countryId\": \"b5ce0efc-d4b5-4b43-84ef-f9d33c79f8d2\", \n\t\t\t\"administrativeAreaLevel1Id\": \"5c970e2e-3134-4ccf-b9c9-693e71155810\", \n\t\t\t\"administrativeAreaLevel2Id\": \"e61d03b1-5035-4a2d-970d-d88cb129e0e2\", \n\t\t\t\"code\": \"1lfo9r5\", \n\t\t\t\"customCode\": \"rh14jg7tq\", \n\t\t\t\"name\": \"Awesome Wooden Bacon\", \n\t\t\t\"slug\": \"aperiam-ipsam-libero\", \n\t\t\t\"latitude\": 54.17969973740366, \n\t\t\t\"longitude\": 418.9408110110385, \n\t\t\t\"zoom\": 8, \n\t\t\t\"mapType\": 'SATELLITE'\n\t\t}, \n\t\t{\n\t\t\t\"id\": \"72815ce5-0db4-4895-beca-90209b2b2c67\", \n\t\t\t\"countryId\": \"b33d8280-6508-449d-85c3-db49c2126053\", \n\t\t\t\"administrativeAreaLevel1Id\": \"716de417-95d8-4c64-b676-6d4235359127\", \n\t\t\t\"administrativeAreaLevel2Id\": \"881a183f-be77-4b07-b692-ec1b33d1c1de\", \n\t\t\t\"code\": \"8vm1os5\", \n\t\t\t\"customCode\": \"579a73vu6\", \n\t\t\t\"name\": \"Handmade Steel Hat\", \n\t\t\t\"slug\": \"qui-sint-qui\", \n\t\t\t\"latitude\": 89.54082019180895, \n\t\t\t\"longitude\": 654.3685915479354, \n\t\t\t\"zoom\": 7, \n\t\t\t\"mapType\": 'ROADMAP'\n\t\t}, \n\t\t{\n\t\t\t\"id\": \"4360ca7d-e4c9-405b-af2a-9464bca30ea8\", \n\t\t\t\"countryId\": \"f8f88412-a0d9-4063-86fe-da5549760ef5\", \n\t\t\t\"administrativeAreaLevel1Id\": \"5e93cce5-4fc7-4c57-aa1c-57797a012687\", \n\t\t\t\"administrativeAreaLevel2Id\": \"153c4a0e-07af-4a48-b84c-187e0bd8f534\", \n\t\t\t\"code\": \"cr3erjh\", \n\t\t\t\"customCode\": \"my2pn650g\", \n\t\t\t\"name\": \"Rustic Metal Pizza\", \n\t\t\t\"slug\": \"sed-qui-vitae\", \n\t\t\t\"latitude\": 39.90606814903412, \n\t\t\t\"longitude\": 649.903860152561, \n\t\t\t\"zoom\": 7, \n\t\t\t\"mapType\": 'ROADMAP'\n\t\t}, \n\t\t{\n\t\t\t\"id\": \"49f45c6c-58dd-4fa2-83e8-b1dd3cb7fb48\", \n\t\t\t\"countryId\": \"acc6b050-f924-4ebc-871a-e24ee533f820\", \n\t\t\t\"administrativeAreaLevel1Id\": \"9b13238e-d497-4d5b-b59a-1a8b6fcc7956\", \n\t\t\t\"administrativeAreaLevel2Id\": \"653dc1e2-ebab-43be-9704-611b2ae97421\", \n\t\t\t\"code\": \"p1y9efi\", \n\t\t\t\"customCode\": \"518dn1jwj\", \n\t\t\t\"name\": \"Sleek Frozen Chair\", \n\t\t\t\"slug\": \"at-quibusdam-soluta\", \n\t\t\t\"latitude\": 94.46854408787098, \n\t\t\t\"longitude\": 164.28665560248947, \n\t\t\t\"zoom\": 4, \n\t\t\t\"mapType\": 'HYBRID'\n\t\t}, \n\t\t{\n\t\t\t\"id\": \"126af12e-6a47-4277-87f0-ad247767f370\", \n\t\t\t\"countryId\": \"98a3d504-e6da-40f4-a3c9-52431a266577\", \n\t\t\t\"administrativeAreaLevel1Id\": \"c5660a8b-b11e-4301-864c-e34be5e9b197\", \n\t\t\t\"administrativeAreaLevel2Id\": \"3cc5fe37-8a56-4f86-ab76-49ad695e632d\", \n\t\t\t\"code\": \"pryp1xm\", \n\t\t\t\"customCode\": \"hc01aaydw\", \n\t\t\t\"name\": \"Intelligent Frozen Pizza\", \n\t\t\t\"slug\": \"suscipit-dicta-iure\", \n\t\t\t\"latitude\": 94.59586622490728, \n\t\t\t\"longitude\": 330.90393627210216, \n\t\t\t\"zoom\": 1, \n\t\t\t\"mapType\": 'ROADMAP'\n\t\t}, \n\t\t{\n\t\t\t\"id\": \"fe4975cc-0129-48b9-8d85-987e0b749d2a\", \n\t\t\t\"countryId\": \"29c11f13-736e-4b67-94f7-3af3bb553b3f\", \n\t\t\t\"administrativeAreaLevel1Id\": \"9312aa97-3da1-4e56-99c9-11694d04ad1b\", \n\t\t\t\"administrativeAreaLevel2Id\": \"97ecedb0-8ef5-449e-8814-4ec26a5e2dd5\", \n\t\t\t\"code\": \"hrauc2p\", \n\t\t\t\"customCode\": \"wf0gz2fz1\", \n\t\t\t\"name\": \"Fantastic Soft Towels\", \n\t\t\t\"slug\": \"doloremque-voluptas-impedit\", \n\t\t\t\"latitude\": 14.81985555350168, \n\t\t\t\"longitude\": 767.7561441123597, \n\t\t\t\"zoom\": 7, \n\t\t\t\"mapType\": 'ROADMAP'\n\t\t}\n\t]\n}"
					}
				},
				"url": {
					"raw": "{{URL}}/graphql",
					"host": [
						"{{URL}}"
					],
					"path": [
						"graphql"
					]
				}
			},
			"response": []
        },
        {
			"name": "GraphQL - commonPaginateAdministrativeAreasLevel3",
			"request": {
				"method": "POST",
				"header": [
                ],
				"body": {
					"mode": "graphql",
					"graphql": {
						"query": "query ($query:QueryStatement $constraint:QueryStatement)\n{\n\tcommonPaginateAdministrativeAreasLevel3 (query:$query constraint:$constraint)\n\t{\n\t\ttotal\n\t\tcount\n\t\trows\n\t}\n}",
						"variables": "{\n\t\"query\":\n\t{\n\t\t\"offset\": 0,\n\t\t\"limit\": 10\n\t}\n}"
					}
				},
				"url": {
					"raw": "{{URL}}/graphql",
					"host": [
						"{{URL}}"
					],
					"path": [
						"graphql"
					]
				}
			},
			"response": []
        },
        {
			"name": "GraphQL - commonGetAdministrativeAreasLevel3",
			"request": {
				"method": "POST",
				"header": [
                ],
				"body": {
					"mode": "graphql",
					"graphql": {
						"query": "query ($query:QueryStatement)\n{\n\tcommonGetAdministrativeAreasLevel3 (query: $query)\n\t{\n\t\tid\n\t\tcode\n\t\tcustomCode\n\t\tname\n\t\tslug\n\t\tlatitude\n\t\tlongitude\n\t\tzoom\n\t\tmapType\n\t\tcreatedAt\n\t\tupdatedAt\n\t}\n}",
						"variables": "{\n\t\"query\":\n\t{\n\t\t\"where\":\n\t\t{ \n\t\t\t\"id\": \"5b19d6ac-4081-573b-96b3-56964d5326a8\"\n\t\t}\n\t}\n}"
					}
				},
				"url": {
					"raw": "{{URL}}/graphql",
					"host": [
						"{{URL}}"
					],
					"path": [
						"graphql"
					]
				}
			},
			"response": []
        },
        {
			"name": "GraphQL - commonFindAdministrativeAreaLevel3",
			"request": {
				"method": "POST",
				"header": [
                ],
				"body": {
					"mode": "graphql",
					"graphql": {
						"query": "query ($query:QueryStatement)\n{\n\tcommonFindAdministrativeAreaLevel3 (query: $query)\n\t{\n\t\tid\n\t\tcode\n\t\tcustomCode\n\t\tname\n\t\tslug\n\t\tlatitude\n\t\tlongitude\n\t\tzoom\n\t\tmapType\n\t\tcreatedAt\n\t\tupdatedAt\n\t}\n}",
						"variables": "{\n\t\"query\":\n\t{\n\t\t\"where\":\n\t\t{\n\t\t\t\"id\": \"5b19d6ac-4081-573b-96b3-56964d5326a8\"\n\t\t}\n\t}\n}"
					}
				},
				"url": {
					"raw": "{{URL}}/graphql",
					"host": [
						"{{URL}}"
					],
					"path": [
						"graphql"
					]
				}
			},
			"response": []
        },
        {
			"name": "GraphQL - commonFindAdministrativeAreaLevel3ById",
			"request": {
				"method": "POST",
				"header": [
                ],
				"body": {
					"mode": "graphql",
					"graphql": {
						"query": "query ($id:ID)\n{\n\tcommonFindAdministrativeAreaLevel3ById (id:$id)\n\t{\n\t\tid\n\t\tcode\n\t\tcustomCode\n\t\tname\n\t\tslug\n\t\tlatitude\n\t\tlongitude\n\t\tzoom\n\t\tmapType\n\t\tcreatedAt\n\t\tupdatedAt\n\t}\n}",
						"variables": "{\n\t\"id\": \"5b19d6ac-4081-573b-96b3-56964d5326a8\"\n}"
					}
				},
				"url": {
					"raw": "{{URL}}/graphql",
					"host": [
						"{{URL}}"
					],
					"path": [
						"graphql"
					]
				}
			},
			"response": []
        },
        {
			"name": "GraphQL - commonUpdateAdministrativeAreaLevel3",
			"request": {
				"method": "POST",
				"header": [
                ],
				"body": {
					"mode": "graphql",
					"graphql": {
						"query": "mutation ($payload:CommonUpdateAdministrativeAreaLevel3Input!)\n{\n\tcommonUpdateAdministrativeAreaLevel3 (payload:$payload)\n\t{\n\t\tid\n\t\tcode\n\t\tcustomCode\n\t\tname\n\t\tslug\n\t\tlatitude\n\t\tlongitude\n\t\tzoom\n\t\tmapType\n\t\tcreatedAt\n\t\tupdatedAt\n\t}\n}",
						"variables": "{\n\t\"payload\":\n\t{\n\t\t\"id\": \"5b19d6ac-4081-573b-96b3-56964d5326a8\", \n\t\t\"countryId\": \"5b19d6ac-4081-573b-96b3-56964d5326a8\", \n\t\t\"administrativeAreaLevel1Id\": \"5b19d6ac-4081-573b-96b3-56964d5326a8\", \n\t\t\"administrativeAreaLevel2Id\": \"5b19d6ac-4081-573b-96b3-56964d5326a8\", \n\t\t\"code\": \"0slyc17\", \n\t\t\"customCode\": \"ru27ui4fo\", \n\t\t\"name\": \"Ergonomic Metal Chicken\", \n\t\t\"slug\": \"odio-nihil-commodi\", \n\t\t\"latitude\": 42.48094939685403, \n\t\t\"longitude\": 350.74856474616274, \n\t\t\"zoom\": 7, \n\t\t\"mapType\": 'TERRAIN'\n\t}\n}"
					}
				},
				"url": {
					"raw": "{{URL}}/graphql",
					"host": [
						"{{URL}}"
					],
					"path": [
						"graphql"
					]
				}
			},
			"response": []
        },
        {
			"name": "GraphQL - commonDeleteAdministrativeAreaLevel3ById",
			"request": {
				"method": "POST",
				"header": [
                ],
				"body": {
					"mode": "graphql",
					"graphql": {
						"query": "mutation ($id:ID!)\n{\n\tcommonDeleteAdministrativeAreaLevel3ById (id:$id)\n\t{\n\t\tid\n\t\tcode\n\t\tcustomCode\n\t\tname\n\t\tslug\n\t\tlatitude\n\t\tlongitude\n\t\tzoom\n\t\tmapType\n\t\tcreatedAt\n\t\tupdatedAt\n\t}\n}",
						"variables": "{\n\t\"id\": \"5b19d6ac-4081-573b-96b3-56964d5326a8\"\n}"
					}
				},
				"url": {
					"raw": "{{URL}}/graphql",
					"host": [
						"{{URL}}"
					],
					"path": [
						"graphql"
					]
				}
			},
			"response": []
        },
        {
			"name": "GraphQL - commonDeleteAdministrativeAreasLevel3",
			"request": {
				"method": "POST",
				"header": [
                ],
				"body": {
					"mode": "graphql",
					"graphql": {
						"query": "mutation ($query:QueryStatement)\n{\n\tcommonDeleteAdministrativeAreasLevel3 (query: $query)\n\t{\n\t\tid\n\t\tcode\n\t\tcustomCode\n\t\tname\n\t\tslug\n\t\tlatitude\n\t\tlongitude\n\t\tzoom\n\t\tmapType\n\t\tcreatedAt\n\t\tupdatedAt\n\t}\n}",
						"variables": "{\n\t\"query\":\n\t{\n\t\t\"where\":\n\t\t{\n\t\t\t\"id\":\n\t\t\t{\n\t\t\t\t\"[substring]\": \"\"\n\t\t\t}\n\t\t}\n\t}\n}"
					}
				},
				"url": {
					"raw": "{{URL}}/graphql",
					"host": [
						"{{URL}}"
					],
					"path": [
						"graphql"
					]
				}
			},
			"response": []
        },
        {
			"name": "REST - common/administrative-area-level-3/create",
			"request": {
				"method": "POST",
				"header": [
					{
						"key"   : "Content-Type",
						"name"  : "Content-Type",
						"type"  : "text",
						"value" : "application/json"
					}				],
				"body": {
					"mode"  : "raw",
					"raw"   : "{\n\t\"id\": \"5b19d6ac-4081-573b-96b3-56964d5326a8\", \n\t\"countryId\": \"5b19d6ac-4081-573b-96b3-56964d5326a8\", \n\t\"administrativeAreaLevel1Id\": \"5b19d6ac-4081-573b-96b3-56964d5326a8\", \n\t\"administrativeAreaLevel2Id\": \"5b19d6ac-4081-573b-96b3-56964d5326a8\", \n\t\"code\": \"c4282oz\", \n\t\"customCode\": \"br4r0cc5r\", \n\t\"name\": \"Sleek Concrete Hat\", \n\t\"slug\": \"ea-exercitationem-provident\", \n\t\"latitude\": 23.98460658937554, \n\t\"longitude\": 450.59102137969137, \n\t\"zoom\": 3, \n\t\"mapType\": 'ROADMAP'\n}",
					"options": {
						"raw": {
							"language": "json"
						}
					}
				},
				"url": {
					"raw": "{{URL}}/common/administrative-area-level-3/create",
					"host": [
						"{{URL}}"
					],
					"path": [
						"common",
						"administrative-area-level-3",
                        "create"
					]
				}
			},
			"response": []
        },
        {
			"name": "REST - common/administrative-areas-level-3/create",
			"request": {
				"method": "POST",
				"header": [
					{
						"key"   : "Content-Type",
						"name"  : "Content-Type",
						"type"  : "text",
						"value" : "application/json"
					}				],
				"body": {
					"mode"  : "raw",
					"raw"   : "[\n\t{\n\t\t\"id\": \"39239c39-9c49-49e8-9e6c-b01aea4b1cb5\", \n\t\t\"countryId\": \"6c457acf-bd97-4827-8123-9c9e12e62f65\", \n\t\t\"administrativeAreaLevel1Id\": \"94ff9e65-6af4-411e-8dea-ed1cc675ee69\", \n\t\t\"administrativeAreaLevel2Id\": \"575a020a-27d3-4839-9cb5-1fd797dc2d3c\", \n\t\t\"code\": \"6d4sdrv\", \n\t\t\"customCode\": \"l9h7n80fn\", \n\t\t\"name\": \"Unbranded Concrete Pants\", \n\t\t\"slug\": \"nesciunt-autem-facere\", \n\t\t\"latitude\": 39.37320454560201, \n\t\t\"longitude\": 171.9488221279258, \n\t\t\"zoom\": 5, \n\t\t\"mapType\": 'HYBRID'\n\t}, \n\t{\n\t\t\"id\": \"ae9ddbaf-c5c0-47a5-8d93-0e32972ed9fd\", \n\t\t\"countryId\": \"0e58be87-9f80-4e6b-ad46-c56dd9b449bb\", \n\t\t\"administrativeAreaLevel1Id\": \"58e74a93-875b-4b83-b444-ca717f6b802a\", \n\t\t\"administrativeAreaLevel2Id\": \"ddba411f-77cc-4ce5-ac45-6b007b7f04d5\", \n\t\t\"code\": \"top7emo\", \n\t\t\"customCode\": \"1n6y4c419\", \n\t\t\"name\": \"Handmade Wooden Hat\", \n\t\t\"slug\": \"ab-quia-voluptatem\", \n\t\t\"latitude\": 59.39292887612801, \n\t\t\"longitude\": 865.5614281457216, \n\t\t\"zoom\": 5, \n\t\t\"mapType\": 'HYBRID'\n\t}, \n\t{\n\t\t\"id\": \"1a29b719-1d24-4431-aed2-1b2953da50f8\", \n\t\t\"countryId\": \"211601b0-22d2-40df-8e17-a3d9b114dc4d\", \n\t\t\"administrativeAreaLevel1Id\": \"35c62ca3-29e1-4cac-95c0-78594ff4cfa9\", \n\t\t\"administrativeAreaLevel2Id\": \"1f7b16f4-2f4a-4976-9c22-1f726f6c4cd4\", \n\t\t\"code\": \"ta5wp7c\", \n\t\t\"customCode\": \"czy11lhck\", \n\t\t\"name\": \"Ergonomic Steel Chair\", \n\t\t\"slug\": \"sit-consectetur-consectetur\", \n\t\t\"latitude\": 28.70580060753507, \n\t\t\"longitude\": 406.5490786632246, \n\t\t\"zoom\": 6, \n\t\t\"mapType\": 'TERRAIN'\n\t}, \n\t{\n\t\t\"id\": \"330274b8-1e5c-4baa-a7bf-7306363c4d7e\", \n\t\t\"countryId\": \"c5efb2e8-5ab4-45f7-85e4-375f1bdf8304\", \n\t\t\"administrativeAreaLevel1Id\": \"e944a6d3-9d3c-41c2-8234-83ed257beefe\", \n\t\t\"administrativeAreaLevel2Id\": \"9a2f5f29-bd8b-4785-95f7-1845a0e53d04\", \n\t\t\"code\": \"93hgn02\", \n\t\t\"customCode\": \"3n4u2f1ye\", \n\t\t\"name\": \"Handmade Metal Computer\", \n\t\t\"slug\": \"reprehenderit-quas-dolores\", \n\t\t\"latitude\": 95.19551108242399, \n\t\t\"longitude\": 851.4229257970777, \n\t\t\"zoom\": 8, \n\t\t\"mapType\": 'ROADMAP'\n\t}, \n\t{\n\t\t\"id\": \"5a50472c-80f5-485d-b15a-d800e7b92bfc\", \n\t\t\"countryId\": \"9985bb0d-38a1-425a-9651-72d926b05b91\", \n\t\t\"administrativeAreaLevel1Id\": \"0cd521ac-0242-45a8-843d-5f500814ec82\", \n\t\t\"administrativeAreaLevel2Id\": \"74c4c621-820d-460e-97f5-06c85804a2f7\", \n\t\t\"code\": \"7nfa50m\", \n\t\t\"customCode\": \"2bagwn98v\", \n\t\t\"name\": \"Sleek Plastic Chair\", \n\t\t\"slug\": \"ipsa-rerum-adipisci\", \n\t\t\"latitude\": 97.90376793477297, \n\t\t\"longitude\": 979.630531558898, \n\t\t\"zoom\": 1, \n\t\t\"mapType\": 'TERRAIN'\n\t}, \n\t{\n\t\t\"id\": \"62c80e34-ac03-430b-baae-79277cb60625\", \n\t\t\"countryId\": \"847b95b9-b9a1-46e6-b00c-02594b64cd09\", \n\t\t\"administrativeAreaLevel1Id\": \"5a17012a-0e9f-4dec-9a0d-3309099ffd2c\", \n\t\t\"administrativeAreaLevel2Id\": \"29c217ed-d353-4a79-9d87-415b23114b3a\", \n\t\t\"code\": \"huqruit\", \n\t\t\"customCode\": \"0j7yr9sr6\", \n\t\t\"name\": \"Practical Rubber Keyboard\", \n\t\t\"slug\": \"a-sed-eaque\", \n\t\t\"latitude\": 64.10424050806873, \n\t\t\"longitude\": 367.7449811449088, \n\t\t\"zoom\": 6, \n\t\t\"mapType\": 'ROADMAP'\n\t}, \n\t{\n\t\t\"id\": \"207e0a87-9eb4-4c8e-9c08-1c79de8ec649\", \n\t\t\"countryId\": \"0719287b-7690-4e41-a09a-afa4ee240ae7\", \n\t\t\"administrativeAreaLevel1Id\": \"a3ecdeed-f4d0-4b31-bb54-e6821260f52c\", \n\t\t\"administrativeAreaLevel2Id\": \"badd200c-16e0-420d-8cd7-1d2c732cbcb9\", \n\t\t\"code\": \"ov98i6e\", \n\t\t\"customCode\": \"j3go4f1f0\", \n\t\t\"name\": \"Handcrafted Plastic Computer\", \n\t\t\"slug\": \"ipsa-voluptatem-qui\", \n\t\t\"latitude\": 48.17381498424575, \n\t\t\"longitude\": 768.6626285359763, \n\t\t\"zoom\": 7, \n\t\t\"mapType\": 'TERRAIN'\n\t}, \n\t{\n\t\t\"id\": \"5e448acf-f3ac-4c0f-be4e-c94d8bc604e5\", \n\t\t\"countryId\": \"2185145a-f553-41ab-a277-ff94fd2af93c\", \n\t\t\"administrativeAreaLevel1Id\": \"e6aa1a4f-8f95-4c0f-adf5-90fce3d372a8\", \n\t\t\"administrativeAreaLevel2Id\": \"437959ba-20bc-4ef0-accc-9910f8dfb0d9\", \n\t\t\"code\": \"gsil7jc\", \n\t\t\"customCode\": \"ue339pm5y\", \n\t\t\"name\": \"Unbranded Steel Keyboard\", \n\t\t\"slug\": \"et-qui-dolores\", \n\t\t\"latitude\": 31.34725221041583, \n\t\t\"longitude\": 192.63324528674931, \n\t\t\"zoom\": 4, \n\t\t\"mapType\": 'TERRAIN'\n\t}, \n\t{\n\t\t\"id\": \"a083ccd2-5760-40bb-ad65-36713a8b8ebe\", \n\t\t\"countryId\": \"4a9c7674-76f7-4b27-a1d1-36960210025b\", \n\t\t\"administrativeAreaLevel1Id\": \"e117f087-cf45-4f54-90a5-e829faf1127e\", \n\t\t\"administrativeAreaLevel2Id\": \"7b5dfe69-7553-4396-b66f-9813ce72af5b\", \n\t\t\"code\": \"cd7uofh\", \n\t\t\"customCode\": \"w3mjgb26w\", \n\t\t\"name\": \"Unbranded Metal Sausages\", \n\t\t\"slug\": \"eum-earum-nemo\", \n\t\t\"latitude\": 71.76438497020904, \n\t\t\"longitude\": 809.3535097616847, \n\t\t\"zoom\": 8, \n\t\t\"mapType\": 'TERRAIN'\n\t}, \n\t{\n\t\t\"id\": \"f897bfb2-4c50-4a43-b30d-42c27b0231d2\", \n\t\t\"countryId\": \"14f0c2a7-249f-4994-865d-c561ec45de58\", \n\t\t\"administrativeAreaLevel1Id\": \"02f6812b-3a7b-44ba-83be-1d76ead298b3\", \n\t\t\"administrativeAreaLevel2Id\": \"ad144839-385a-4e99-acc8-e54e5c3fd656\", \n\t\t\"code\": \"rd1hbw4\", \n\t\t\"customCode\": \"ca8o2g484\", \n\t\t\"name\": \"Handcrafted Plastic Computer\", \n\t\t\"slug\": \"nemo-soluta-voluptatibus\", \n\t\t\"latitude\": 10.45779651627318, \n\t\t\"longitude\": 496.17841792238625, \n\t\t\"zoom\": 2, \n\t\t\"mapType\": 'TERRAIN'\n\t}\n]",
					"options": {
						"raw": {
							"language": "json"
						}
					}
				},
				"url": {
					"raw": "{{URL}}/common/administrative-areas-level-3/create",
					"host": [
						"{{URL}}"
					],
					"path": [
						"common",
						"administrative-areas-level-3",
                        "create"
					]
				}
			},
			"response": []
        },
        {
			"name": "REST - common/administrative-areas-level-3/paginate",
			"protocolProfileBehavior": {
				"disableBodyPruning": true
			},
			"request": {
				"method": "POST",
				"header": [
					{
						"key": "Content-Type",
						"name": "Content-Type",
						"type": "text",
						"value": "application/json"
					}				],
				"body": {
					"mode": "raw",
					"raw": "{\n\t\"query\":\n\t{\n\t\t\"offset\": 0,\n\t\t\"limit\": 10\n\t}\n}",
					"options": {
						"raw": {
							"language": "json"
						}
					}
				},
				"url": {
					"raw": "{{URL}}/common/administrative-areas-level-3/paginate",
					"host": [
						"{{URL}}"
					],
					"path": [
						"common",
                        "administrative-areas-level-3",
                        "paginate"
					]
				}
			},
			"response": []
        },
        {
			"name": "REST - common/administrative-areas-level-3/get",
			"protocolProfileBehavior": {
				"disableBodyPruning": true
			},
			"request": {
				"method": "POST",
				"header": [
					{
						"key": "Content-Type",
						"name": "Content-Type",
						"type": "text",
						"value": "application/json"
					}				],
				"body": {
					"mode": "raw",
					"raw": "{\n\t\"query\":\n\t{\n\t\t\"where\":\n\t\t{ \n\t\t\t\"id\": \"5b19d6ac-4081-573b-96b3-56964d5326a8\"\n\t\t}\n\t}\n}",
					"options": {
						"raw": {
							"language": "json"
						}
					}
				},
				"url": {
					"raw": "{{URL}}/common/administrative-areas-level-3/get",
					"host": [
						"{{URL}}"
					],
					"path": [
						"common",
						"administrative-areas-level-3",
                        "get"
					]
				}
			},
			"response": []
        },
        {
			"name": "REST - common/administrative-area-level-3/find",
			"protocolProfileBehavior": {
				"disableBodyPruning": true
			},
			"request": {
				"method": "POST",
				"header": [
					{
						"key": "Content-Type",
						"name": "Content-Type",
						"type": "text",
						"value": "application/json"
					}				],
				"body": {
					"mode": "raw",
					"raw": "{\n\t\"query\":\n\t{\n\t\t\"where\":\n\t\t{\n\t\t\t\"id\": \"5b19d6ac-4081-573b-96b3-56964d5326a8\"\n\t\t}\n\t}\n}",
					"options": {
						"raw": {
							"language": "json"
						}
					}
				},
				"url": {
					"raw": "{{URL}}/common/administrative-area-level-3/find",
					"host": [
						"{{URL}}"
					],
					"path": [
						"common",
						"administrative-area-level-3",
                        "find"
					]
				}
			},
			"response": []
        },
        {
			"name": "REST - common/administrative-area-level-3/find/{id}",
			"protocolProfileBehavior": {
				"disableBodyPruning": true
			},
			"request": {
				"method": "POST",
				"header": [
					{
						"key": "Content-Type",
						"name": "Content-Type",
						"type": "text",
						"value": "application/json"
					}				],
				"body": {
					"mode": "raw",
					"raw": "",
					"options": {
						"raw": {
							"language": "json"
						}
					}
				},
				"url": {
					"raw": "{{URL}}/common/administrative-area-level-3/find/5b19d6ac-4081-573b-96b3-56964d5326a8",
					"host": [
						"{{URL}}"
					],
					"path": [
						"common",
						"administrative-area-level-3",
                        "find",
						"5b19d6ac-4081-573b-96b3-56964d5326a8"
					]
				}
			},
			"response": []
        },
        {
			"name": "REST - common/administrative-area-level-3/update",
			"request": {
				"method": "PUT",
				"header": [
					{
						"key": "Content-Type",
						"name": "Content-Type",
						"type": "text",
						"value": "application/json"
					}				],
				"body": {
					"mode": "raw",
					"raw"   : "{\n\t\"id\": \"5b19d6ac-4081-573b-96b3-56964d5326a8\", \n\t\"countryId\": \"5b19d6ac-4081-573b-96b3-56964d5326a8\", \n\t\"administrativeAreaLevel1Id\": \"5b19d6ac-4081-573b-96b3-56964d5326a8\", \n\t\"administrativeAreaLevel2Id\": \"5b19d6ac-4081-573b-96b3-56964d5326a8\", \n\t\"code\": \"vx87p42\", \n\t\"customCode\": \"7pxkyu23v\", \n\t\"name\": \"Generic Frozen Tuna\", \n\t\"slug\": \"numquam-ullam-non\", \n\t\"latitude\": 54.15320806434153, \n\t\"longitude\": 813.3498694969492, \n\t\"zoom\": 9, \n\t\"mapType\": 'TERRAIN'\n}",
					"options": {
						"raw": {
							"language": "json"
						}
					}
				},
				"url": {
					"raw": "{{URL}}/common/administrative-area-level-3/update",
					"host": [
						"{{URL}}"
					],
					"path": [
						"common",
						"administrative-area-level-3",
                        "update"
					]
				}
			},
			"response": []
        },
        {
			"name": "REST - common/administrative-area-level-3/delete/{id}",
			"request": {
				"method": "DELETE",
				"header": [
					{
						"key": "Content-Type",
						"name": "Content-Type",
						"type": "text",
						"value": "application/json"
					}				],
				"body": {
					"mode": "raw",
					"raw": "",
					"options": {
						"raw": {
							"language": "json"
						}
					}
				},
				"url": {
					"raw": "{{URL}}/common/administrative-area-level-3/delete/5b19d6ac-4081-573b-96b3-56964d5326a8",
					"host": [
						"{{URL}}"
					],
					"path": [
						"common",
						"administrative-area-level-3",
                        "delete",
						"5b19d6ac-4081-573b-96b3-56964d5326a8"
					]
				}
			},
			"response": []
		},
        {
			"name": "REST - common/administrative-areas-level-3/delete",
			"request": {
				"method": "DELETE",
				"header": [
					{
						"key": "Content-Type",
						"name": "Content-Type",
						"type": "text",
						"value": "application/json"
					}				],
				"body": {
					"mode": "raw",
					"raw": "{\n\t\"query\":\n\t{\n\t\t\"where\":\n\t\t{\n\t\t\t\"id\":\n\t\t\t{\n\t\t\t\t\"[substring]\": \"\"\n\t\t\t}\n\t\t}\n\t}\n}",
					"options": {
						"raw": {
							"language": "json"
						}
					}
				},
				"url": {
					"raw": "{{URL}}/common/administrative-areas-level-3/delete",
					"host": [
						"{{URL}}"
					],
					"path": [
						"common",
						"administrative-areas-level-3",
                        "delete"
					]
				}
			},
			"response": []
		}
    ],
    "variable": [
		{
			"id": "d9bc3afc-fd40-5505-b57f-8f5d5118e01b",
			"key": "URL",
			"value": "http://localhost:8080",
			"type": "string"
		}
	]
}