{
    "info": {
		"_postman_id"   : "abb0befe-62c2-4157-84ea-3a999bc2a1d7",
		"name"          : "@apps - o-auth/scope",
		"schema"        : "https://schema.getpostman.com/json/collection/v2.1.0/collection.json"
    },
    "item": [
        {
			"name": "GraphQL - oAuthCreateScope",
			"request": {
				"method": "POST",
				"header": [
                ],
				"body": {
					"mode": "graphql",
					"graphql": {
						"query": "mutation ($payload:OAuthCreateScopeInput!)\n{\n\toAuthCreateScope (payload:$payload)\n\t{\n\t\tid\n\t\tcode\n\t\tname\n\t}\n}",
                        "variables": "{\n\t\"payload\":\n\t{\n\t\t\"id\": \"5b19d6ac-4081-573b-96b3-56964d5326a8\", \n\t\t\"code\": \"zuilgqmjbjpuxqxrpbm\", \n\t\t\"name\": \"Incredible Wooden Shirt\"\n\t}\n}"
					}
				},
				"url": {
					"raw": "{{URL}}/graphql",
					"host": [
						"{{URL}}"
					],
					"path": [
						"graphql"
					]
				}
			},
			"response": []
        },
        {
			"name": "GraphQL - oAuthCreateScopes",
			"request": {
				"method": "POST",
				"header": [],
				"body": {
					"mode": "graphql",
					"graphql": {
						"query": "mutation ($payload:[OAuthCreateScopeInput]!)\n{\n\toAuthCreateScopes (payload:$payload)\n}",
						"variables": "{\n\t\"payload\":\n\t[\n\t\t{\n\t\t\t\"id\": \"6b7eb40e-e595-460b-8939-692c8131a057\", \n\t\t\t\"code\": \"p9lixhgsiizrf7bifn7\", \n\t\t\t\"name\": \"Refined Rubber Car\"\n\t\t}, \n\t\t{\n\t\t\t\"id\": \"96849f32-e633-48b8-b330-f4027e75c3d8\", \n\t\t\t\"code\": \"ehtm4dn6bgxc359ehuo\", \n\t\t\t\"name\": \"Sleek Cotton Computer\"\n\t\t}, \n\t\t{\n\t\t\t\"id\": \"29578466-8649-45d8-8430-a517b4866076\", \n\t\t\t\"code\": \"rdmg1a820fxqpzmxpdw\", \n\t\t\t\"name\": \"Incredible Granite Car\"\n\t\t}, \n\t\t{\n\t\t\t\"id\": \"00e59503-1995-4e42-97cf-4405435f0500\", \n\t\t\t\"code\": \"dmvzhc7gw026shffkby\", \n\t\t\t\"name\": \"Handmade Fresh Sausages\"\n\t\t}, \n\t\t{\n\t\t\t\"id\": \"cd9cec2e-ef60-4566-af51-bac3c4969a25\", \n\t\t\t\"code\": \"pymnnsd8gldtcdk9t1f\", \n\t\t\t\"name\": \"Unbranded Fresh Table\"\n\t\t}, \n\t\t{\n\t\t\t\"id\": \"87f3618d-c2e8-4c18-af68-4c934c294d8d\", \n\t\t\t\"code\": \"nihgnlv9er4mm49cgyw\", \n\t\t\t\"name\": \"Handmade Fresh Bike\"\n\t\t}, \n\t\t{\n\t\t\t\"id\": \"2781482c-7e5c-4cc2-a79a-603d64ce4cc5\", \n\t\t\t\"code\": \"hbilzg8zui063b1yuho\", \n\t\t\t\"name\": \"Handcrafted Granite Sausages\"\n\t\t}, \n\t\t{\n\t\t\t\"id\": \"4d42d53a-5d76-4234-8b67-b84c13916533\", \n\t\t\t\"code\": \"9y5lsq2y2pp4irnsntg\", \n\t\t\t\"name\": \"Tasty Fresh Ball\"\n\t\t}, \n\t\t{\n\t\t\t\"id\": \"28c4712a-c594-4a38-aef5-8c9d430cdbd8\", \n\t\t\t\"code\": \"w9rf2u3du9613in4et0\", \n\t\t\t\"name\": \"Refined Steel Pants\"\n\t\t}, \n\t\t{\n\t\t\t\"id\": \"9be386ee-125c-496d-9e43-bef1814e34cb\", \n\t\t\t\"code\": \"kd770tivcmsjmazjd93\", \n\t\t\t\"name\": \"Unbranded Wooden Shirt\"\n\t\t}\n\t]\n}"
					}
				},
				"url": {
					"raw": "{{URL}}/graphql",
					"host": [
						"{{URL}}"
					],
					"path": [
						"graphql"
					]
				}
			},
			"response": []
        },
        {
			"name": "GraphQL - oAuthPaginateScopes",
			"request": {
				"method": "POST",
				"header": [
                ],
				"body": {
					"mode": "graphql",
					"graphql": {
						"query": "query ($query:QueryStatement $constraint:QueryStatement)\n{\n\toAuthPaginateScopes (query:$query constraint:$constraint)\n\t{\n\t\ttotal\n\t\tcount\n\t\trows\n\t}\n}",
						"variables": "{\n\t\"query\":\n\t{\n\t\t\"offset\": 0,\n\t\t\"limit\": 10\n\t}\n}"
					}
				},
				"url": {
					"raw": "{{URL}}/graphql",
					"host": [
						"{{URL}}"
					],
					"path": [
						"graphql"
					]
				}
			},
			"response": []
        },
        {
			"name": "GraphQL - oAuthGetScopes",
			"request": {
				"method": "POST",
				"header": [
                ],
				"body": {
					"mode": "graphql",
					"graphql": {
						"query": "query ($query:QueryStatement)\n{\n\toAuthGetScopes (query: $query)\n\t{\n\t\tid\n\t\tcode\n\t\tname\n\t\tcreatedAt\n\t\tupdatedAt\n\t}\n}",
						"variables": "{\n\t\"query\":\n\t{\n\t\t\"where\":\n\t\t{ \n\t\t\t\"id\": \"5b19d6ac-4081-573b-96b3-56964d5326a8\"\n\t\t}\n\t}\n}"
					}
				},
				"url": {
					"raw": "{{URL}}/graphql",
					"host": [
						"{{URL}}"
					],
					"path": [
						"graphql"
					]
				}
			},
			"response": []
        },
        {
			"name": "GraphQL - oAuthFindScope",
			"request": {
				"method": "POST",
				"header": [
                ],
				"body": {
					"mode": "graphql",
					"graphql": {
						"query": "query ($query:QueryStatement)\n{\n\toAuthFindScope (query: $query)\n\t{\n\t\tid\n\t\tcode\n\t\tname\n\t\tcreatedAt\n\t\tupdatedAt\n\t}\n}",
						"variables": "{\n\t\"query\":\n\t{\n\t\t\"where\":\n\t\t{\n\t\t\t\"id\": \"5b19d6ac-4081-573b-96b3-56964d5326a8\"\n\t\t}\n\t}\n}"
					}
				},
				"url": {
					"raw": "{{URL}}/graphql",
					"host": [
						"{{URL}}"
					],
					"path": [
						"graphql"
					]
				}
			},
			"response": []
        },
        {
			"name": "GraphQL - oAuthFindScopeById",
			"request": {
				"method": "POST",
				"header": [
                ],
				"body": {
					"mode": "graphql",
					"graphql": {
						"query": "query ($id:ID)\n{\n\toAuthFindScopeById (id:$id)\n\t{\n\t\tid\n\t\tcode\n\t\tname\n\t\tcreatedAt\n\t\tupdatedAt\n\t}\n}",
						"variables": "{\n\t\"id\": \"5b19d6ac-4081-573b-96b3-56964d5326a8\"\n}"
					}
				},
				"url": {
					"raw": "{{URL}}/graphql",
					"host": [
						"{{URL}}"
					],
					"path": [
						"graphql"
					]
				}
			},
			"response": []
        },
        {
			"name": "GraphQL - oAuthUpdateScope",
			"request": {
				"method": "POST",
				"header": [
                ],
				"body": {
					"mode": "graphql",
					"graphql": {
						"query": "mutation ($payload:OAuthUpdateScopeInput!)\n{\n\toAuthUpdateScope (payload:$payload)\n\t{\n\t\tid\n\t\tcode\n\t\tname\n\t\tcreatedAt\n\t\tupdatedAt\n\t}\n}",
						"variables": "{\n\t\"payload\":\n\t{\n\t\t\"id\": \"5b19d6ac-4081-573b-96b3-56964d5326a8\", \n\t\t\"code\": \"r5zzgckjiumtc198jl0\", \n\t\t\"name\": \"Tasty Steel Shirt\"\n\t}\n}"
					}
				},
				"url": {
					"raw": "{{URL}}/graphql",
					"host": [
						"{{URL}}"
					],
					"path": [
						"graphql"
					]
				}
			},
			"response": []
        },
        {
			"name": "GraphQL - oAuthDeleteScopeById",
			"request": {
				"method": "POST",
				"header": [
                ],
				"body": {
					"mode": "graphql",
					"graphql": {
						"query": "mutation ($id:ID!)\n{\n\toAuthDeleteScopeById (id:$id)\n\t{\n\t\tid\n\t\tcode\n\t\tname\n\t\tcreatedAt\n\t\tupdatedAt\n\t}\n}",
						"variables": "{\n\t\"id\": \"5b19d6ac-4081-573b-96b3-56964d5326a8\"\n}"
					}
				},
				"url": {
					"raw": "{{URL}}/graphql",
					"host": [
						"{{URL}}"
					],
					"path": [
						"graphql"
					]
				}
			},
			"response": []
        },
        {
			"name": "GraphQL - oAuthDeleteScopes",
			"request": {
				"method": "POST",
				"header": [
                ],
				"body": {
					"mode": "graphql",
					"graphql": {
						"query": "mutation ($query:QueryStatement)\n{\n\toAuthDeleteScopes (query: $query)\n\t{\n\t\tid\n\t\tcode\n\t\tname\n\t\tcreatedAt\n\t\tupdatedAt\n\t}\n}",
						"variables": "{\n\t\"query\":\n\t{\n\t\t\"where\":\n\t\t{\n\t\t\t\"id\":\n\t\t\t{\n\t\t\t\t\"[substring]\": \"\"\n\t\t\t}\n\t\t}\n\t}\n}"
					}
				},
				"url": {
					"raw": "{{URL}}/graphql",
					"host": [
						"{{URL}}"
					],
					"path": [
						"graphql"
					]
				}
			},
			"response": []
        },
        {
			"name": "REST - o-auth/scope/create",
			"request": {
				"method": "POST",
				"header": [
					{
						"key"   : "Content-Type",
						"name"  : "Content-Type",
						"type"  : "text",
						"value" : "application/json"
					}				],
				"body": {
					"mode"  : "raw",
					"raw"   : "{\n\t\"id\": \"5b19d6ac-4081-573b-96b3-56964d5326a8\", \n\t\"code\": \"7mu7j226qrptlay27go\", \n\t\"name\": \"Sleek Cotton Chicken\"\n}",
					"options": {
						"raw": {
							"language": "json"
						}
					}
				},
				"url": {
					"raw": "{{URL}}/o-auth/scope/create",
					"host": [
						"{{URL}}"
					],
					"path": [
						"o-auth",
						"scope",
                        "create"
					]
				}
			},
			"response": []
        },
        {
			"name": "REST - o-auth/scopes/create",
			"request": {
				"method": "POST",
				"header": [
					{
						"key"   : "Content-Type",
						"name"  : "Content-Type",
						"type"  : "text",
						"value" : "application/json"
					}				],
				"body": {
					"mode"  : "raw",
					"raw"   : "[\n\t{\n\t\t\"id\": \"c8e32dab-6b80-4996-b6fc-1e23db5f6103\", \n\t\t\"code\": \"ramlfiuhw8i30cbk6ox\", \n\t\t\"name\": \"Ergonomic Steel Bike\"\n\t}, \n\t{\n\t\t\"id\": \"3aed268c-0230-4fc5-9529-816891bc2842\", \n\t\t\"code\": \"r2lbsomqvnw9iqc6830\", \n\t\t\"name\": \"Licensed Plastic Pizza\"\n\t}, \n\t{\n\t\t\"id\": \"ccd91857-e106-40a5-a86d-a248d75d8753\", \n\t\t\"code\": \"sxk2gqshveip4aj5ogs\", \n\t\t\"name\": \"Sleek Metal Chicken\"\n\t}, \n\t{\n\t\t\"id\": \"352d8e56-6f4e-4b18-86b2-e23c3554d07a\", \n\t\t\"code\": \"iq9lqkxpuj2wry6gtsm\", \n\t\t\"name\": \"Refined Frozen Gloves\"\n\t}, \n\t{\n\t\t\"id\": \"30249812-1066-4293-b419-2cd4161d746d\", \n\t\t\"code\": \"eu6sjm10u0aduhfcnvo\", \n\t\t\"name\": \"Tasty Frozen Table\"\n\t}, \n\t{\n\t\t\"id\": \"fc7e8e0b-8b4d-438d-a220-73a795e3877c\", \n\t\t\"code\": \"sipdwfuwzrh0i9m3nes\", \n\t\t\"name\": \"Fantastic Metal Chicken\"\n\t}, \n\t{\n\t\t\"id\": \"97527de6-3cab-4e6a-adba-084e0a8d18fe\", \n\t\t\"code\": \"vu0q5a7x5w7rc6oe099\", \n\t\t\"name\": \"Awesome Cotton Chair\"\n\t}, \n\t{\n\t\t\"id\": \"e7909edd-c62a-413f-bccc-11624ea816df\", \n\t\t\"code\": \"jagdfi763250pz36ma6\", \n\t\t\"name\": \"Practical Frozen Salad\"\n\t}, \n\t{\n\t\t\"id\": \"16feb670-fd08-4188-86a7-a9d7255550db\", \n\t\t\"code\": \"hfwwbbudcsdq5iai8jr\", \n\t\t\"name\": \"Practical Cotton Pizza\"\n\t}, \n\t{\n\t\t\"id\": \"fd8fff24-4f06-484a-9269-9a482b2f41ec\", \n\t\t\"code\": \"3mrhrlpyrjkoouts7tp\", \n\t\t\"name\": \"Handcrafted Cotton Gloves\"\n\t}\n]",
					"options": {
						"raw": {
							"language": "json"
						}
					}
				},
				"url": {
					"raw": "{{URL}}/o-auth/scopes/create",
					"host": [
						"{{URL}}"
					],
					"path": [
						"o-auth",
						"scopes",
                        "create"
					]
				}
			},
			"response": []
        },
        {
			"name": "REST - o-auth/scopes/paginate",
			"protocolProfileBehavior": {
				"disableBodyPruning": true
			},
			"request": {
				"method": "POST",
				"header": [
					{
						"key": "Content-Type",
						"name": "Content-Type",
						"type": "text",
						"value": "application/json"
					}				],
				"body": {
					"mode": "raw",
					"raw": "{\n\t\"query\":\n\t{\n\t\t\"offset\": 0,\n\t\t\"limit\": 10\n\t}\n}",
					"options": {
						"raw": {
							"language": "json"
						}
					}
				},
				"url": {
					"raw": "{{URL}}/o-auth/scopes/paginate",
					"host": [
						"{{URL}}"
					],
					"path": [
						"o-auth",
                        "scopes",
                        "paginate"
					]
				}
			},
			"response": []
        },
        {
			"name": "REST - o-auth/scopes/get",
			"protocolProfileBehavior": {
				"disableBodyPruning": true
			},
			"request": {
				"method": "POST",
				"header": [
					{
						"key": "Content-Type",
						"name": "Content-Type",
						"type": "text",
						"value": "application/json"
					}				],
				"body": {
					"mode": "raw",
					"raw": "{\n\t\"query\":\n\t{\n\t\t\"where\":\n\t\t{ \n\t\t\t\"id\": \"5b19d6ac-4081-573b-96b3-56964d5326a8\"\n\t\t}\n\t}\n}",
					"options": {
						"raw": {
							"language": "json"
						}
					}
				},
				"url": {
					"raw": "{{URL}}/o-auth/scopes/get",
					"host": [
						"{{URL}}"
					],
					"path": [
						"o-auth",
						"scopes",
                        "get"
					]
				}
			},
			"response": []
        },
        {
			"name": "REST - o-auth/scope/find",
			"protocolProfileBehavior": {
				"disableBodyPruning": true
			},
			"request": {
				"method": "POST",
				"header": [
					{
						"key": "Content-Type",
						"name": "Content-Type",
						"type": "text",
						"value": "application/json"
					}				],
				"body": {
					"mode": "raw",
					"raw": "{\n\t\"query\":\n\t{\n\t\t\"where\":\n\t\t{\n\t\t\t\"id\": \"5b19d6ac-4081-573b-96b3-56964d5326a8\"\n\t\t}\n\t}\n}",
					"options": {
						"raw": {
							"language": "json"
						}
					}
				},
				"url": {
					"raw": "{{URL}}/o-auth/scope/find",
					"host": [
						"{{URL}}"
					],
					"path": [
						"o-auth",
						"scope",
                        "find"
					]
				}
			},
			"response": []
        },
        {
			"name": "REST - o-auth/scope/find/{id}",
			"protocolProfileBehavior": {
				"disableBodyPruning": true
			},
			"request": {
				"method": "GET",
				"header": [
					{
						"key": "Content-Type",
						"name": "Content-Type",
						"type": "text",
						"value": "application/json"
					}				],
				"body": {
					"mode": "raw",
					"raw": "",
					"options": {
						"raw": {
							"language": "json"
						}
					}
				},
				"url": {
					"raw": "{{URL}}/o-auth/scope/find/5b19d6ac-4081-573b-96b3-56964d5326a8",
					"host": [
						"{{URL}}"
					],
					"path": [
						"o-auth",
						"scope",
                        "find",
						"5b19d6ac-4081-573b-96b3-56964d5326a8"
					]
				}
			},
			"response": []
        },
        {
			"name": "REST - o-auth/scope/update",
			"request": {
				"method": "PUT",
				"header": [
					{
						"key": "Content-Type",
						"name": "Content-Type",
						"type": "text",
						"value": "application/json"
					}				],
				"body": {
					"mode": "raw",
					"raw"   : "{\n\t\"id\": \"5b19d6ac-4081-573b-96b3-56964d5326a8\", \n\t\"code\": \"ql310iysxe6dttqch6k\", \n\t\"name\": \"Rustic Concrete Gloves\"\n}",
					"options": {
						"raw": {
							"language": "json"
						}
					}
				},
				"url": {
					"raw": "{{URL}}/o-auth/scope/update",
					"host": [
						"{{URL}}"
					],
					"path": [
						"o-auth",
						"scope",
                        "update"
					]
				}
			},
			"response": []
        },
        {
			"name": "REST - o-auth/scope/delete/{id}",
			"request": {
				"method": "DELETE",
				"header": [
					{
						"key": "Content-Type",
						"name": "Content-Type",
						"type": "text",
						"value": "application/json"
					}				],
				"body": {
					"mode": "raw",
					"raw": "",
					"options": {
						"raw": {
							"language": "json"
						}
					}
				},
				"url": {
					"raw": "{{URL}}/o-auth/scope/delete/5b19d6ac-4081-573b-96b3-56964d5326a8",
					"host": [
						"{{URL}}"
					],
					"path": [
						"o-auth",
						"scope",
                        "delete",
						"5b19d6ac-4081-573b-96b3-56964d5326a8"
					]
				}
			},
			"response": []
		},
        {
			"name": "REST - o-auth/scopes/delete",
			"request": {
				"method": "DELETE",
				"header": [
					{
						"key": "Content-Type",
						"name": "Content-Type",
						"type": "text",
						"value": "application/json"
					}				],
				"body": {
					"mode": "raw",
					"raw": "{\n\t\"query\":\n\t{\n\t\t\"where\":\n\t\t{\n\t\t\t\"id\":\n\t\t\t{\n\t\t\t\t\"[substring]\": \"\"\n\t\t\t}\n\t\t}\n\t}\n}",
					"options": {
						"raw": {
							"language": "json"
						}
					}
				},
				"url": {
					"raw": "{{URL}}/o-auth/scopes/delete",
					"host": [
						"{{URL}}"
					],
					"path": [
						"o-auth",
						"scopes",
                        "delete"
					]
				}
			},
			"response": []
		}
    ],
    "variable": [
		{
			"id": "a21ac759-94a6-4bee-8f15-048e6df10146",
			"key": "URL",
			"value": "http://localhost:8080",
			"type": "string"
		}
	]
}